[{"id":"242","idx":"92","date":"1434753152","gallery_idx":"37","file":"https:\/\/youtu.be\/qIQECDIXJ7g","filev":"files\/photo\/9170c5defa8c55750dc618ad49fdcaf7.jpg","media_type":"video","title":"Support to Micro and Small Enterprises","description":"Not defined","filesize":"0","insert_admin":"1","position":"1","lang":"5","status":"0","x":"37"},{"id":"302","idx":"112","date":"1435058402","gallery_idx":"37","file":"https:\/\/youtu.be\/Pw5gf2R1yRY","filev":"files\/photo\/8b1a93db3356c030842438529a73f012.jpg","media_type":"video","title":"Enterprise Georgia","description":"Not defined","filesize":"0","insert_admin":"1","position":"2","lang":"5","status":"0","x":"37"}]